[
  {
    "features": [
      "highway",
      "maxspeed",
      "hour",
      "centrality"
    ],
    "target": "speed_kph_p85"
  },
  {
    "features": [
      "highway",
      "maxspeed",
      "hour",
      "centrality",
      "tweets_50_hour"
    ],
    "target": "speed_kph_p85"
  },
  {
    "features": [
      "highway",
      "maxspeed",
      "hour",
      "centrality",
      "tweets_50_all"
    ],
    "target": "speed_kph_p85"
  },
  {
    "features": [
      "highway",
      "maxspeed",
      "hour",
      "centrality",
      "tweets_100_hour"
    ],
    "target": "speed_kph_p85"
  },
  {
    "features": [
      "highway",
      "maxspeed",
      "hour",
      "centrality",
      "tweets_100_all"
    ],
    "target": "speed_kph_p85"
  },
  {
    "features": [
      "highway",
      "maxspeed",
      "hour",
      "centrality",
      "tweets_250_hour"
    ],
    "target": "speed_kph_p85"
  },
  {
    "features": [
      "highway",
      "maxspeed",
      "hour",
      "centrality",
      "tweets_250_all"
    ],
    "target": "speed_kph_p85"
  },
  {
    "features": [
      "highway",
      "maxspeed",
      "hour",
      "centrality",
      "tweets_500_hour"
    ],
    "target": "speed_kph_p85"
  },
  {
    "features": [
      "highway",
      "maxspeed",
      "hour",
      "centrality",
      "tweets_500_all"
    ],
    "target": "speed_kph_p85"
  }
]
